{
  "project_info": {
    "project_number": "628177216395",
    "firebase_url": "https://driverhiring-d9381-default-rtdb.firebaseio.com",
    "project_id": "driverhiring-d9381",
    "storage_bucket": "driverhiring-d9381.appspot.com"
  },
  "client": [
    {
      "client_info": {
        "mobilesdk_app_id": "1:628177216395:android:878e72516380e565d5458e",
        "android_client_info": {
          "package_name": "com.example.driverhiring"
        }
      },
      "oauth_client": [
        {
          "client_id": "628177216395-5kd8hr1faomatka7gsofcfco155hdjam.apps.googleusercontent.com",
          "client_type": 3
        }
      ],
      "api_key": [
        {
          "current_key": "AIzaSyA7TtCws-Apmk7fsplUrQel00sQRgv01w4"
        }
      ],
      "services": {
        "appinvite_service": {
          "other_platform_oauth_client": [
            {
              "client_id": "628177216395-5kd8hr1faomatka7gsofcfco155hdjam.apps.googleusercontent.com",
              "client_type": 3
            }
          ]
        }
      }
    },
    {
      "client_info": {
        "mobilesdk_app_id": "1:628177216395:android:2bfb9394045387c8d5458e",
        "android_client_info": {
          "package_name": "com.example.driverhiring1"
        }
      },
      "oauth_client": [
        {
          "client_id": "628177216395-5kd8hr1faomatka7gsofcfco155hdjam.apps.googleusercontent.com",
          "client_type": 3
        }
      ],
      "api_key": [
        {
          "current_key": "AIzaSyA7TtCws-Apmk7fsplUrQel00sQRgv01w4"
        }
      ],
      "services": {
        "appinvite_service": {
          "other_platform_oauth_client": [
            {
              "client_id": "628177216395-5kd8hr1faomatka7gsofcfco155hdjam.apps.googleusercontent.com",
              "client_type": 3
            }
          ]
        }
      }
    },
    {
      "client_info": {
        "mobilesdk_app_id": "1:628177216395:android:981fb4c400c02c46d5458e",
        "android_client_info": {
          "package_name": "com.example.sampleapplication"
        }
      },
      "oauth_client": [
        {
          "client_id": "628177216395-5kd8hr1faomatka7gsofcfco155hdjam.apps.googleusercontent.com",
          "client_type": 3
        }
      ],
      "api_key": [
        {
          "current_key": "AIzaSyA7TtCws-Apmk7fsplUrQel00sQRgv01w4"
        }
      ],
      "services": {
        "appinvite_service": {
          "other_platform_oauth_client": [
            {
              "client_id": "628177216395-5kd8hr1faomatka7gsofcfco155hdjam.apps.googleusercontent.com",
              "client_type": 3
            }
          ]
        }
      }
    },
    {
      "client_info": {
        "mobilesdk_app_id": "1:628177216395:android:70c67167ecbfa0efd5458e",
        "android_client_info": {
          "package_name": "com.example.selectqurey"
        }
      },
      "oauth_client": [
        {
          "client_id": "628177216395-5kd8hr1faomatka7gsofcfco155hdjam.apps.googleusercontent.com",
          "client_type": 3
        }
      ],
      "api_key": [
        {
          "current_key": "AIzaSyA7TtCws-Apmk7fsplUrQel00sQRgv01w4"
        }
      ],
      "services": {
        "appinvite_service": {
          "other_platform_oauth_client": [
            {
              "client_id": "628177216395-5kd8hr1faomatka7gsofcfco155hdjam.apps.googleusercontent.com",
              "client_type": 3
            }
          ]
        }
      }
    }
  ],
  "configuration_version": "1"
}